uncvalue/__init__.py
uncvalue/uncvalue.py
uncvalue-0.1.1.dist-info/LICENSE
uncvalue-0.1.1.dist-info/METADATA
uncvalue-0.1.1.dist-info/WHEEL
uncvalue-0.1.1.dist-info/top_level.txt
uncvalue-0.1.1.dist-info/RECORD
