Metadata-Version: 2.1
Name: uncvalue
Version: 0.1.1
Summary: Simple python class to propagate uncertainty in calculations.
Home-page: https://github.com/Physics-Simulations/UncValue
Author: Physics Simulations
Author-email: apuntsdefisica@gmail.com
License: UNKNOWN
Platform: UNKNOWN
Classifier: Programming Language :: Python :: 3
Classifier: License :: OSI Approved :: Apache Software License
Classifier: Operating System :: OS Independent
Classifier: Topic :: Scientific/Engineering :: Mathematics
Requires-Python: >=3.6
Requires-Dist: numpy (>=1.18)
